warmup/DivisionCircuit.v
module Division(
	input         clock,
	input         start,
	input  [N-1:0] a,
	input  [N-1:0] b,
	output [N-1:0] q,
	output [N-1:0] r
);

parameter N = 32;

reg [N-1:0] R, B, Q;
integer counter;

assign q = Q;
assign r = R;

  always @(posedge clock) begin
      if (start) begin
		counter = N;
		R <= 0;
		B <= b;
		Q <= a;
	  end
	  else if (counter >= 0) begin
		counter = counter - 1;
		R = {R[N-2:0], a[counter]};
			if (R < B) begin
				Q[counter] = 1'b0;
			end
			else begin
				Q[counter] = 1'b1;
				R = R - B;
			end
	  end
  end

endmodule

warmup/DivisionTestbench.v
module DivisionTestbench();

	// Generate input stimuli
	reg clk, s;
	wire [31:0] qres;
	wire [31:0] rres;

	initial
	begin
		s <= 1'b0; #1; s <= 1'b1; #4; s <= 1'b0; #160; $finish;
	end

	always
	begin
		clk <= 1'b1; #2; clk <= 1'b0; #2;
	end

	// Module under test
	Division divider(
		.clock(clk),
		.start(s),
		.a(32'd25), // TODO Feel free to try out other values!
		.b(32'd7),
		.q(qres),
		.r(rres)
	);

	// Test that 32 cycles (which take 4 time units each) after the start (at
	// time 4) the correct result has been calculated.
	initial
	begin
		$dumpfile("divsim.vcd");
		$dumpvars;
		#133;
		if (qres == 32'd3 && rres == 32'd4)
			$display("Simulation succeeded");
		else
			$display("Simulation failed");
	end

endmodule

divsim.vcd
$date
	Fri Jun 16 14:40:52 2023
$end
$version
	Icarus Verilog
$end
$timescale
	1s
$end
$scope module DivisionTestbench $end
$var wire 32 ! rres [31:0] $end
$var wire 32 " qres [31:0] $end
$var reg 1 # clk $end
$var reg 1 $ s $end
$scope module divider $end
$var wire 32 % a [31:0] $end
$var wire 32 & b [31:0] $end
$var wire 1 # clock $end
$var wire 32 ' q [31:0] $end
$var wire 32 ( r [31:0] $end
$var wire 1 $ start $end
$var reg 32 ) B [31:0] $end
$var reg 32 * Q [31:0] $end
$var reg 32 + R [31:0] $end
$var integer 32 , counter [31:0] $end
$upscope $end
$upscope $end
$enddefinitions $end
#0
$dumpvars
bx ,
bx +
bx *
bx )
bx (
bx '
b111 &
b11001 %
0$
1#
bx "
bx !
$end
#1
1$
#2
0#
#4
b11001 "
b11001 '
b11001 *
b111 )
b0 !
b0 (
b0 +
b100000 ,
1#
#5
0$
#6
0#
#8
b11111 ,
1#
#10
0#
#12
b11110 ,
1#
#14
0#
#16
b11101 ,
1#
#18
0#
#20
b11100 ,
1#
#22
0#
#24
b11011 ,
1#
#26
0#
#28
b11010 ,
1#
#30
0#
#32
b11001 ,
1#
#34
0#
#36
b11000 ,
1#
#38
0#
#40
b10111 ,
1#
#42
0#
#44
b10110 ,
1#
#46
0#
#48
b10101 ,
1#
#50
0#
#52
b10100 ,
1#
#54
0#
#56
b10011 ,
1#
#58
0#
#60
b10010 ,
1#
#62
0#
#64
b10001 ,
1#
#66
0#
#68
b10000 ,
1#
#70
0#
#72
b1111 ,
1#
#74
0#
#76
b1110 ,
1#
#78
0#
#80
b1101 ,
1#
#82
0#
#84
b1100 ,
1#
#86
0#
#88
b1011 ,
1#
#90
0#
#92
b1010 ,
1#
#94
0#
#96
b1001 ,
1#
#98
0#
#100
b1000 ,
1#
#102
0#
#104
b111 ,
1#
#106
0#
#108
b110 ,
1#
#110
0#
#112
b101 ,
1#
#114
0#
#116
b1001 "
b1001 '
b1001 *
b1 !
b1 (
b1 +
b100 ,
1#
#118
0#
#120
b1 "
b1 '
b1 *
b11 !
b11 (
b11 +
b11 ,
1#
#122
0#
#124
b110 !
b110 (
b110 +
b10 ,
1#
#126
0#
#128
b11 "
b11 '
b11 *
b101 !
b101 (
b101 +
b1 ,
1#
#130
0#
#132
b100 !
b100 (
b100 +
b0 ,
1#
#134
0#
#136
bx !
bx (
bx +
b11111111111111111111111111111111 ,
1#
